src/__init__.py
src/main.py
series_renamer_tools-1.0.5.dist-info/LICENSE
series_renamer_tools-1.0.5.dist-info/METADATA
series_renamer_tools-1.0.5.dist-info/WHEEL
series_renamer_tools-1.0.5.dist-info/entry_points.txt
series_renamer_tools-1.0.5.dist-info/top_level.txt
series_renamer_tools-1.0.5.dist-info/RECORD
