Metadata-Version: 2.1
Name: series-renamer-tools
Version: 1.0.5
Summary: Series Renamer: rename files of series with respect to episode number.
Home-page: https://github.com/seehait/series-renamer-tools
License: MIT
Platform: UNKNOWN
Classifier: Development Status :: 5 - Production/Stable
Classifier: Intended Audience :: End Users/Desktop
Classifier: License :: OSI Approved :: MIT License
Classifier: Programming Language :: Python :: 3 :: Only
Classifier: Topic :: Utilities
Requires-Dist: natsort (==7.0.1)
